<list>
  <ProcessDefinition>
    <processDefinitionPK>
      <companyId>1</companyId>
      <processId>wf_cadastro_compra_item_novo</processId>
    </processDefinitionPK>
    <processDescription>Cadastro e compra de item novo</processDescription>
    <instruction></instruction>
    <active>true</active>
    <publicProcess>false</publicProcess>
    <volumeId>Default</volumeId>
    <categoryId>Compras</categoryId>
    <managerEngineAllocationId>Usuário</managerEngineAllocationId>
    <managerEngineAllocationConfiguration>&lt;AssignmentController&gt;&lt;User&gt;209&lt;/User&gt;&lt;/AssignmentController&gt;</managerEngineAllocationConfiguration>
    <snapshotFrequency>0</snapshotFrequency>
    <baseDay>0</baseDay>
    <baseMonth>0</baseMonth>
    <periodId>Default</periodId>
    <uniqueCardVersion>false</uniqueCardVersion>
    <keyWord></keyWord>
    <complementsLevel>2</complementsLevel>
    <notifyRequisitionerComplements>true</notifyRequisitionerComplements>
    <notifyManagerComplements>true</notifyManagerComplements>
    <deadlineTime>0</deadlineTime>
    <warningDeadlineTime>0</warningDeadlineTime>
    <notifyAuthorityComplements>true</notifyAuthorityComplements>
  </ProcessDefinition>
  <ProcessDefinitionVersion>
    <processDefinitionVersionPK>
      <companyId>1</companyId>
      <processId>Cadastro e compra de item novo</processId>
      <version>28</version>
    </processDefinitionVersionPK>
    <versionDescription></versionDescription>
    <formId>0</formId>
    <editionMode>true</editionMode>
    <updateAttachmentsVersion>false</updateAttachmentsVersion>
    <controlsAttachmentsSecurity>false</controlsAttachmentsSecurity>
    <active>true</active>
    <blockedVersion>false</blockedVersion>
    <counterSign>false</counterSign>
    <openInstances>0</openInstances>
    <bpmnVersion>1</bpmnVersion>
    <processStates/>
    <favorito>false</favorito>
    <inheritFormSecurity>true</inheritFormSecurity>
    <mobileReady>true</mobileReady>
  </ProcessDefinitionVersion>
  <list>
    <ProcessState>
      <processStatePK>
        <companyId>1</companyId>
        <processId>wf_cadastro_compra_item_novo</processId>
        <version>1</version>
        <sequence>3</sequence>
      </processStatePK>
      <stateName>Início</stateName>
      <stateDescription>Início</stateDescription>
      <instruction>Veja bem, você só deverá preencher os itens que deseja alterar, se não for alterar o campo, deixá-lo vazio.</instruction>
      <deadlineTime>0</deadlineTime>
      <joint>false</joint>
      <agreementPercentage>0</agreementPercentage>
      <engineAllocationId></engineAllocationId>
      <engineAllocationConfiguration></engineAllocationConfiguration>
      <selectColleague>1</selectColleague>
      <initialState>true</initialState>
      <notifyAuthorityDelay>false</notifyAuthorityDelay>
      <notifyRequisitionerDelay>false</notifyRequisitionerDelay>
      <allowanceAuthorityTime>0</allowanceAuthorityTime>
      <frequenceAuthorityTime>0</frequenceAuthorityTime>
      <allowanceRequisitionerTime>0</allowanceRequisitionerTime>
      <frequenceRequisitionerTime>0</frequenceRequisitionerTime>
      <transferAttachments>false</transferAttachments>
      <subProcessId></subProcessId>
      <formFolder>0</formFolder>
      <notifyAuthorityFollowUp>true</notifyAuthorityFollowUp>
      <notifyRequisitionerFollowUp>false</notifyRequisitionerFollowUp>
      <automatic>false</automatic>
      <positionX>71</positionX>
      <positionY>75</positionY>
      <forecastedEffortType>0</forecastedEffortType>
      <forecastedEffort>0</forecastedEffort>
      <notifyManagerFollowUp>false</notifyManagerFollowUp>
      <notifyManagerDelay>false</notifyManagerDelay>
      <allowanceManagerTime>0</allowanceManagerTime>
      <frequenceManagerTime>0</frequenceManagerTime>
      <inhibitTransfer>false</inhibitTransfer>
      <periodId></periodId>
      <stateType>0</stateType>
      <bpmnType>10</bpmnType>
      <signalId>0</signalId>
      <counterSign>false</counterSign>
      <openInstances>0</openInstances>
      <noticeExpirationAuthorityTime>0</noticeExpirationAuthorityTime>
      <noticeExpirationRequisitionerTime>0</noticeExpirationRequisitionerTime>
      <noticeExpirationManagerTime>0</noticeExpirationManagerTime>
      <destinationStates/>
      <digitalSignature>false</digitalSignature>
    </ProcessState>
    <ProcessState>
      <processStatePK>
        <companyId>1</companyId>
        <processId>wf_cadastro_compra_item_novo</processId>
        <version>1</version>
        <sequence>10</sequence>
      </processStatePK>
      <stateName>Liberação no recebimento</stateName>
      <stateDescription>Liberação no recebimento</stateDescription>
      <instruction></instruction>
      <deadlineTime>7200</deadlineTime>
      <deadlineFieldName></deadlineFieldName>
      <joint>false</joint>
      <agreementPercentage>0</agreementPercentage>
      <engineAllocationId>Pool Papel</engineAllocationId>
      <engineAllocationConfiguration>&lt;AssignmentController&gt;&lt;Role&gt;RECEBIMENTO&lt;/Role&gt;&lt;/AssignmentController&gt;</engineAllocationConfiguration>
      <selectColleague>1</selectColleague>
      <initialState>false</initialState>
      <notifyAuthorityDelay>true</notifyAuthorityDelay>
      <notifyRequisitionerDelay>false</notifyRequisitionerDelay>
      <allowanceAuthorityTime>3600</allowanceAuthorityTime>
      <frequenceAuthorityTime>3600</frequenceAuthorityTime>
      <allowanceRequisitionerTime>0</allowanceRequisitionerTime>
      <frequenceRequisitionerTime>0</frequenceRequisitionerTime>
      <transferAttachments>false</transferAttachments>
      <subProcessId></subProcessId>
      <formFolder>0</formFolder>
      <notifyAuthorityFollowUp>true</notifyAuthorityFollowUp>
      <notifyRequisitionerFollowUp>false</notifyRequisitionerFollowUp>
      <automatic>false</automatic>
      <positionX>891</positionX>
      <positionY>335</positionY>
      <forecastedEffortType>0</forecastedEffortType>
      <forecastedEffort>0</forecastedEffort>
      <notifyManagerFollowUp>false</notifyManagerFollowUp>
      <notifyManagerDelay>false</notifyManagerDelay>
      <allowanceManagerTime>0</allowanceManagerTime>
      <frequenceManagerTime>0</frequenceManagerTime>
      <inhibitTransfer>false</inhibitTransfer>
      <periodId></periodId>
      <stateType>0</stateType>
      <bpmnType>80</bpmnType>
      <signalId>0</signalId>
      <counterSign>false</counterSign>
      <openInstances>0</openInstances>
      <noticeExpirationAuthorityTime>0</noticeExpirationAuthorityTime>
      <noticeExpirationRequisitionerTime>0</noticeExpirationRequisitionerTime>
      <noticeExpirationManagerTime>0</noticeExpirationManagerTime>
      <destinationStates/>
      <digitalSignature>false</digitalSignature>
      <executionType>0</executionType>
    </ProcessState>
    <ProcessState>
      <processStatePK>
        <companyId>1</companyId>
        <processId>wf_cadastro_compra_item_novo</processId>
        <version>1</version>
        <sequence>20</sequence>
      </processStatePK>
      <stateName>Cadastro e envio do código</stateName>
      <stateDescription>Cadastro e envio do código</stateDescription>
      <instruction></instruction>
      <deadlineTime>14400</deadlineTime>
      <deadlineFieldName></deadlineFieldName>
      <joint>false</joint>
      <agreementPercentage>0</agreementPercentage>
      <engineAllocationId>Usuário</engineAllocationId>
      <engineAllocationConfiguration>&lt;AssignmentController&gt;&lt;User&gt;467&lt;/User&gt;&lt;/AssignmentController&gt;</engineAllocationConfiguration>
      <selectColleague>1</selectColleague>
      <initialState>false</initialState>
      <notifyAuthorityDelay>true</notifyAuthorityDelay>
      <notifyRequisitionerDelay>true</notifyRequisitionerDelay>
      <allowanceAuthorityTime>600</allowanceAuthorityTime>
      <frequenceAuthorityTime>300</frequenceAuthorityTime>
      <allowanceRequisitionerTime>600</allowanceRequisitionerTime>
      <frequenceRequisitionerTime>300</frequenceRequisitionerTime>
      <transferAttachments>false</transferAttachments>
      <subProcessId></subProcessId>
      <formFolder>0</formFolder>
      <notifyAuthorityFollowUp>true</notifyAuthorityFollowUp>
      <notifyRequisitionerFollowUp>false</notifyRequisitionerFollowUp>
      <automatic>false</automatic>
      <positionX>121</positionX>
      <positionY>184</positionY>
      <forecastedEffortType>0</forecastedEffortType>
      <forecastedEffort>0</forecastedEffort>
      <notifyManagerFollowUp>false</notifyManagerFollowUp>
      <notifyManagerDelay>false</notifyManagerDelay>
      <allowanceManagerTime>0</allowanceManagerTime>
      <frequenceManagerTime>0</frequenceManagerTime>
      <inhibitTransfer>false</inhibitTransfer>
      <periodId></periodId>
      <stateType>0</stateType>
      <bpmnType>80</bpmnType>
      <signalId>0</signalId>
      <counterSign>false</counterSign>
      <openInstances>0</openInstances>
      <noticeExpirationAuthorityTime>60</noticeExpirationAuthorityTime>
      <noticeExpirationRequisitionerTime>60</noticeExpirationRequisitionerTime>
      <noticeExpirationManagerTime>0</noticeExpirationManagerTime>
      <destinationStates/>
      <digitalSignature>false</digitalSignature>
      <executionType>0</executionType>
    </ProcessState>
    <ProcessState>
      <processStatePK>
        <companyId>1</companyId>
        <processId>wf_cadastro_compra_item_novo</processId>
        <version>1</version>
        <sequence>37</sequence>
      </processStatePK>
      <stateName>Compras-01</stateName>
      <stateDescription>Compras-01</stateDescription>
      <instruction></instruction>
      <deadlineTime>14400</deadlineTime>
      <deadlineFieldName></deadlineFieldName>
      <joint>false</joint>
      <agreementPercentage>0</agreementPercentage>
      <engineAllocationId>Campo Formulário</engineAllocationId>
      <engineAllocationConfiguration>&lt;AssignmentController&gt;&lt;FormField&gt;matcompras1&lt;/FormField&gt;&lt;/AssignmentController&gt;</engineAllocationConfiguration>
      <selectColleague>1</selectColleague>
      <initialState>false</initialState>
      <notifyAuthorityDelay>true</notifyAuthorityDelay>
      <notifyRequisitionerDelay>false</notifyRequisitionerDelay>
      <allowanceAuthorityTime>3600</allowanceAuthorityTime>
      <frequenceAuthorityTime>3600</frequenceAuthorityTime>
      <allowanceRequisitionerTime>0</allowanceRequisitionerTime>
      <frequenceRequisitionerTime>0</frequenceRequisitionerTime>
      <transferAttachments>false</transferAttachments>
      <subProcessId></subProcessId>
      <formFolder>0</formFolder>
      <notifyAuthorityFollowUp>true</notifyAuthorityFollowUp>
      <notifyRequisitionerFollowUp>false</notifyRequisitionerFollowUp>
      <automatic>false</automatic>
      <positionX>128</positionX>
      <positionY>470</positionY>
      <forecastedEffortType>0</forecastedEffortType>
      <forecastedEffort>0</forecastedEffort>
      <notifyManagerFollowUp>false</notifyManagerFollowUp>
      <notifyManagerDelay>false</notifyManagerDelay>
      <allowanceManagerTime>0</allowanceManagerTime>
      <frequenceManagerTime>0</frequenceManagerTime>
      <inhibitTransfer>false</inhibitTransfer>
      <periodId></periodId>
      <stateType>0</stateType>
      <bpmnType>80</bpmnType>
      <signalId>0</signalId>
      <counterSign>false</counterSign>
      <openInstances>0</openInstances>
      <noticeExpirationAuthorityTime>0</noticeExpirationAuthorityTime>
      <noticeExpirationRequisitionerTime>0</noticeExpirationRequisitionerTime>
      <noticeExpirationManagerTime>0</noticeExpirationManagerTime>
      <destinationStates/>
      <digitalSignature>false</digitalSignature>
      <executionType>0</executionType>
    </ProcessState>
    <ProcessState>
      <processStatePK>
        <companyId>1</companyId>
        <processId>wf_cadastro_compra_item_novo</processId>
        <version>1</version>
        <sequence>73</sequence>
      </processStatePK>
      <stateName>Colocação do pedido</stateName>
      <stateDescription>Colocação do pedido</stateDescription>
      <instruction></instruction>
      <deadlineTime>14400</deadlineTime>
      <deadlineFieldName></deadlineFieldName>
      <joint>false</joint>
      <agreementPercentage>0</agreementPercentage>
      <engineAllocationId>Executor Atividade</engineAllocationId>
      <engineAllocationConfiguration>&lt;AssignmentController&gt;&lt;BaseActivity&gt;3&lt;/BaseActivity&gt;&lt;Returns&gt;First&lt;/Returns&gt;&lt;/AssignmentController&gt;</engineAllocationConfiguration>
      <selectColleague>1</selectColleague>
      <initialState>false</initialState>
      <notifyAuthorityDelay>true</notifyAuthorityDelay>
      <notifyRequisitionerDelay>false</notifyRequisitionerDelay>
      <allowanceAuthorityTime>3600</allowanceAuthorityTime>
      <frequenceAuthorityTime>3600</frequenceAuthorityTime>
      <allowanceRequisitionerTime>0</allowanceRequisitionerTime>
      <frequenceRequisitionerTime>0</frequenceRequisitionerTime>
      <transferAttachments>false</transferAttachments>
      <subProcessId></subProcessId>
      <formFolder>0</formFolder>
      <notifyAuthorityFollowUp>true</notifyAuthorityFollowUp>
      <notifyRequisitionerFollowUp>false</notifyRequisitionerFollowUp>
      <automatic>false</automatic>
      <positionX>231</positionX>
      <positionY>42</positionY>
      <forecastedEffortType>0</forecastedEffortType>
      <forecastedEffort>0</forecastedEffort>
      <notifyManagerFollowUp>false</notifyManagerFollowUp>
      <notifyManagerDelay>false</notifyManagerDelay>
      <allowanceManagerTime>0</allowanceManagerTime>
      <frequenceManagerTime>0</frequenceManagerTime>
      <inhibitTransfer>false</inhibitTransfer>
      <periodId></periodId>
      <stateType>0</stateType>
      <bpmnType>80</bpmnType>
      <signalId>0</signalId>
      <counterSign>false</counterSign>
      <openInstances>0</openInstances>
      <noticeExpirationAuthorityTime>0</noticeExpirationAuthorityTime>
      <noticeExpirationRequisitionerTime>0</noticeExpirationRequisitionerTime>
      <noticeExpirationManagerTime>0</noticeExpirationManagerTime>
      <destinationStates/>
      <digitalSignature>false</digitalSignature>
      <executionType>0</executionType>
    </ProcessState>
    <ProcessState>
      <processStatePK>
        <companyId>1</companyId>
        <processId>wf_cadastro_compra_item_novo</processId>
        <version>1</version>
        <sequence>75</sequence>
      </processStatePK>
      <stateName>Remoção do rastreio</stateName>
      <stateDescription>Remoção do rastreio</stateDescription>
      <instruction></instruction>
      <deadlineTime>7200</deadlineTime>
      <deadlineFieldName></deadlineFieldName>
      <joint>false</joint>
      <agreementPercentage>0</agreementPercentage>
      <engineAllocationId>Pool Papel</engineAllocationId>
      <engineAllocationConfiguration>&lt;AssignmentController&gt;&lt;Role&gt;CADASTRO_COMPRAS&lt;/Role&gt;&lt;/AssignmentController&gt;</engineAllocationConfiguration>
      <selectColleague>1</selectColleague>
      <initialState>false</initialState>
      <notifyAuthorityDelay>true</notifyAuthorityDelay>
      <notifyRequisitionerDelay>false</notifyRequisitionerDelay>
      <allowanceAuthorityTime>3600</allowanceAuthorityTime>
      <frequenceAuthorityTime>3600</frequenceAuthorityTime>
      <allowanceRequisitionerTime>0</allowanceRequisitionerTime>
      <frequenceRequisitionerTime>0</frequenceRequisitionerTime>
      <transferAttachments>false</transferAttachments>
      <subProcessId></subProcessId>
      <formFolder>0</formFolder>
      <notifyAuthorityFollowUp>true</notifyAuthorityFollowUp>
      <notifyRequisitionerFollowUp>false</notifyRequisitionerFollowUp>
      <automatic>false</automatic>
      <positionX>981</positionX>
      <positionY>188</positionY>
      <forecastedEffortType>0</forecastedEffortType>
      <forecastedEffort>0</forecastedEffort>
      <notifyManagerFollowUp>false</notifyManagerFollowUp>
      <notifyManagerDelay>false</notifyManagerDelay>
      <allowanceManagerTime>0</allowanceManagerTime>
      <frequenceManagerTime>0</frequenceManagerTime>
      <inhibitTransfer>false</inhibitTransfer>
      <periodId></periodId>
      <stateType>0</stateType>
      <bpmnType>80</bpmnType>
      <signalId>0</signalId>
      <counterSign>false</counterSign>
      <openInstances>0</openInstances>
      <noticeExpirationAuthorityTime>0</noticeExpirationAuthorityTime>
      <noticeExpirationRequisitionerTime>0</noticeExpirationRequisitionerTime>
      <noticeExpirationManagerTime>0</noticeExpirationManagerTime>
      <destinationStates/>
      <digitalSignature>false</digitalSignature>
      <executionType>0</executionType>
    </ProcessState>
    <ProcessState>
      <processStatePK>
        <companyId>1</companyId>
        <processId>wf_cadastro_compra_item_novo</processId>
        <version>1</version>
        <sequence>81</sequence>
      </processStatePK>
      <stateName>Follow-up do material</stateName>
      <stateDescription>Follow-up do material</stateDescription>
      <instruction></instruction>
      <deadlineTime>57600</deadlineTime>
      <deadlineFieldName></deadlineFieldName>
      <joint>false</joint>
      <agreementPercentage>0</agreementPercentage>
      <engineAllocationId>Pool Papel</engineAllocationId>
      <engineAllocationConfiguration>&lt;AssignmentController&gt;&lt;Role&gt;CADASTRO_COMPRAS&lt;/Role&gt;&lt;/AssignmentController&gt;</engineAllocationConfiguration>
      <selectColleague>1</selectColleague>
      <initialState>false</initialState>
      <notifyAuthorityDelay>true</notifyAuthorityDelay>
      <notifyRequisitionerDelay>false</notifyRequisitionerDelay>
      <allowanceAuthorityTime>3600</allowanceAuthorityTime>
      <frequenceAuthorityTime>3600</frequenceAuthorityTime>
      <allowanceRequisitionerTime>0</allowanceRequisitionerTime>
      <frequenceRequisitionerTime>0</frequenceRequisitionerTime>
      <transferAttachments>false</transferAttachments>
      <subProcessId></subProcessId>
      <formFolder>0</formFolder>
      <notifyAuthorityFollowUp>true</notifyAuthorityFollowUp>
      <notifyRequisitionerFollowUp>false</notifyRequisitionerFollowUp>
      <automatic>false</automatic>
      <positionX>791</positionX>
      <positionY>188</positionY>
      <forecastedEffortType>0</forecastedEffortType>
      <forecastedEffort>0</forecastedEffort>
      <notifyManagerFollowUp>false</notifyManagerFollowUp>
      <notifyManagerDelay>false</notifyManagerDelay>
      <allowanceManagerTime>0</allowanceManagerTime>
      <frequenceManagerTime>0</frequenceManagerTime>
      <inhibitTransfer>false</inhibitTransfer>
      <periodId></periodId>
      <stateType>0</stateType>
      <bpmnType>80</bpmnType>
      <signalId>0</signalId>
      <counterSign>false</counterSign>
      <openInstances>0</openInstances>
      <noticeExpirationAuthorityTime>0</noticeExpirationAuthorityTime>
      <noticeExpirationRequisitionerTime>0</noticeExpirationRequisitionerTime>
      <noticeExpirationManagerTime>0</noticeExpirationManagerTime>
      <destinationStates/>
      <digitalSignature>false</digitalSignature>
      <executionType>0</executionType>
    </ProcessState>
    <ProcessState>
      <processStatePK>
        <companyId>1</companyId>
        <processId>wf_cadastro_compra_item_novo</processId>
        <version>1</version>
        <sequence>85</sequence>
      </processStatePK>
      <stateName>Vendedor libera o pedido</stateName>
      <stateDescription>Vendedor libera o pedido</stateDescription>
      <instruction></instruction>
      <deadlineTime>7200</deadlineTime>
      <deadlineFieldName></deadlineFieldName>
      <joint>false</joint>
      <agreementPercentage>0</agreementPercentage>
      <engineAllocationId>Executor Atividade</engineAllocationId>
      <engineAllocationConfiguration>&lt;AssignmentController&gt;&lt;BaseActivity&gt;3&lt;/BaseActivity&gt;&lt;Returns&gt;First&lt;/Returns&gt;&lt;/AssignmentController&gt;</engineAllocationConfiguration>
      <selectColleague>1</selectColleague>
      <initialState>false</initialState>
      <notifyAuthorityDelay>true</notifyAuthorityDelay>
      <notifyRequisitionerDelay>false</notifyRequisitionerDelay>
      <allowanceAuthorityTime>3600</allowanceAuthorityTime>
      <frequenceAuthorityTime>3600</frequenceAuthorityTime>
      <allowanceRequisitionerTime>0</allowanceRequisitionerTime>
      <frequenceRequisitionerTime>0</frequenceRequisitionerTime>
      <transferAttachments>false</transferAttachments>
      <subProcessId></subProcessId>
      <formFolder>0</formFolder>
      <notifyAuthorityFollowUp>true</notifyAuthorityFollowUp>
      <notifyRequisitionerFollowUp>false</notifyRequisitionerFollowUp>
      <automatic>false</automatic>
      <positionX>1071</positionX>
      <positionY>50</positionY>
      <forecastedEffortType>0</forecastedEffortType>
      <forecastedEffort>0</forecastedEffort>
      <notifyManagerFollowUp>false</notifyManagerFollowUp>
      <notifyManagerDelay>false</notifyManagerDelay>
      <allowanceManagerTime>0</allowanceManagerTime>
      <frequenceManagerTime>0</frequenceManagerTime>
      <inhibitTransfer>false</inhibitTransfer>
      <periodId></periodId>
      <stateType>0</stateType>
      <bpmnType>80</bpmnType>
      <signalId>0</signalId>
      <counterSign>false</counterSign>
      <openInstances>0</openInstances>
      <noticeExpirationAuthorityTime>0</noticeExpirationAuthorityTime>
      <noticeExpirationRequisitionerTime>0</noticeExpirationRequisitionerTime>
      <noticeExpirationManagerTime>0</noticeExpirationManagerTime>
      <destinationStates/>
      <digitalSignature>false</digitalSignature>
      <executionType>0</executionType>
    </ProcessState>
    <ProcessState>
      <processStatePK>
        <companyId>1</companyId>
        <processId>wf_cadastro_compra_item_novo</processId>
        <version>1</version>
        <sequence>87</sequence>
      </processStatePK>
      <stateName>Número NF</stateName>
      <stateDescription>Número NF</stateDescription>
      <instruction></instruction>
      <deadlineTime>14400</deadlineTime>
      <deadlineFieldName></deadlineFieldName>
      <joint>false</joint>
      <agreementPercentage>0</agreementPercentage>
      <engineAllocationId>Pool Papel</engineAllocationId>
      <engineAllocationConfiguration>&lt;AssignmentController&gt;&lt;Role&gt;CADASTRO_COMPRAS&lt;/Role&gt;&lt;/AssignmentController&gt;</engineAllocationConfiguration>
      <selectColleague>1</selectColleague>
      <initialState>false</initialState>
      <notifyAuthorityDelay>true</notifyAuthorityDelay>
      <notifyRequisitionerDelay>false</notifyRequisitionerDelay>
      <allowanceAuthorityTime>3600</allowanceAuthorityTime>
      <frequenceAuthorityTime>3600</frequenceAuthorityTime>
      <allowanceRequisitionerTime>0</allowanceRequisitionerTime>
      <frequenceRequisitionerTime>0</frequenceRequisitionerTime>
      <transferAttachments>false</transferAttachments>
      <subProcessId></subProcessId>
      <formFolder>0</formFolder>
      <notifyAuthorityFollowUp>true</notifyAuthorityFollowUp>
      <notifyRequisitionerFollowUp>false</notifyRequisitionerFollowUp>
      <automatic>false</automatic>
      <positionX>1151</positionX>
      <positionY>195</positionY>
      <forecastedEffortType>0</forecastedEffortType>
      <forecastedEffort>0</forecastedEffort>
      <notifyManagerFollowUp>false</notifyManagerFollowUp>
      <notifyManagerDelay>false</notifyManagerDelay>
      <allowanceManagerTime>0</allowanceManagerTime>
      <frequenceManagerTime>0</frequenceManagerTime>
      <inhibitTransfer>false</inhibitTransfer>
      <periodId></periodId>
      <stateType>0</stateType>
      <bpmnType>80</bpmnType>
      <signalId>0</signalId>
      <counterSign>false</counterSign>
      <openInstances>0</openInstances>
      <noticeExpirationAuthorityTime>0</noticeExpirationAuthorityTime>
      <noticeExpirationRequisitionerTime>0</noticeExpirationRequisitionerTime>
      <noticeExpirationManagerTime>0</noticeExpirationManagerTime>
      <destinationStates/>
      <digitalSignature>false</digitalSignature>
      <executionType>0</executionType>
    </ProcessState>
    <ProcessState>
      <processStatePK>
        <companyId>1</companyId>
        <processId>wf_cadastro_compra_item_novo</processId>
        <version>1</version>
        <sequence>93</sequence>
      </processStatePK>
      <stateName>Compras-02</stateName>
      <stateDescription>Compras-02</stateDescription>
      <instruction></instruction>
      <deadlineTime>0</deadlineTime>
      <deadlineFieldName></deadlineFieldName>
      <joint>false</joint>
      <agreementPercentage>0</agreementPercentage>
      <engineAllocationId>Campo Formulário</engineAllocationId>
      <engineAllocationConfiguration>&lt;AssignmentController&gt;&lt;FormField&gt;matcompras2&lt;/FormField&gt;&lt;/AssignmentController&gt;</engineAllocationConfiguration>
      <selectColleague>1</selectColleague>
      <initialState>false</initialState>
      <notifyAuthorityDelay>true</notifyAuthorityDelay>
      <notifyRequisitionerDelay>false</notifyRequisitionerDelay>
      <allowanceAuthorityTime>3600</allowanceAuthorityTime>
      <frequenceAuthorityTime>3600</frequenceAuthorityTime>
      <allowanceRequisitionerTime>0</allowanceRequisitionerTime>
      <frequenceRequisitionerTime>0</frequenceRequisitionerTime>
      <transferAttachments>false</transferAttachments>
      <subProcessId></subProcessId>
      <formFolder>0</formFolder>
      <notifyAuthorityFollowUp>true</notifyAuthorityFollowUp>
      <notifyRequisitionerFollowUp>false</notifyRequisitionerFollowUp>
      <automatic>false</automatic>
      <positionX>291</positionX>
      <positionY>470</positionY>
      <forecastedEffortType>0</forecastedEffortType>
      <forecastedEffort>0</forecastedEffort>
      <notifyManagerFollowUp>false</notifyManagerFollowUp>
      <notifyManagerDelay>false</notifyManagerDelay>
      <allowanceManagerTime>0</allowanceManagerTime>
      <frequenceManagerTime>0</frequenceManagerTime>
      <inhibitTransfer>false</inhibitTransfer>
      <periodId></periodId>
      <stateType>0</stateType>
      <bpmnType>80</bpmnType>
      <signalId>0</signalId>
      <counterSign>false</counterSign>
      <openInstances>0</openInstances>
      <noticeExpirationAuthorityTime>0</noticeExpirationAuthorityTime>
      <noticeExpirationRequisitionerTime>0</noticeExpirationRequisitionerTime>
      <noticeExpirationManagerTime>0</noticeExpirationManagerTime>
      <destinationStates/>
      <digitalSignature>false</digitalSignature>
      <executionType>0</executionType>
    </ProcessState>
    <ProcessState>
      <processStatePK>
        <companyId>1</companyId>
        <processId>wf_cadastro_compra_item_novo</processId>
        <version>1</version>
        <sequence>94</sequence>
      </processStatePK>
      <stateName>Compras-03</stateName>
      <stateDescription>Compras-03</stateDescription>
      <instruction></instruction>
      <deadlineTime>0</deadlineTime>
      <deadlineFieldName></deadlineFieldName>
      <joint>false</joint>
      <agreementPercentage>0</agreementPercentage>
      <engineAllocationId>Campo Formulário</engineAllocationId>
      <engineAllocationConfiguration>&lt;AssignmentController&gt;&lt;FormField&gt;matcompras3&lt;/FormField&gt;&lt;/AssignmentController&gt;</engineAllocationConfiguration>
      <selectColleague>1</selectColleague>
      <initialState>false</initialState>
      <notifyAuthorityDelay>true</notifyAuthorityDelay>
      <notifyRequisitionerDelay>false</notifyRequisitionerDelay>
      <allowanceAuthorityTime>3600</allowanceAuthorityTime>
      <frequenceAuthorityTime>3600</frequenceAuthorityTime>
      <allowanceRequisitionerTime>0</allowanceRequisitionerTime>
      <frequenceRequisitionerTime>0</frequenceRequisitionerTime>
      <transferAttachments>false</transferAttachments>
      <subProcessId></subProcessId>
      <formFolder>0</formFolder>
      <notifyAuthorityFollowUp>true</notifyAuthorityFollowUp>
      <notifyRequisitionerFollowUp>false</notifyRequisitionerFollowUp>
      <automatic>false</automatic>
      <positionX>441</positionX>
      <positionY>470</positionY>
      <forecastedEffortType>0</forecastedEffortType>
      <forecastedEffort>0</forecastedEffort>
      <notifyManagerFollowUp>false</notifyManagerFollowUp>
      <notifyManagerDelay>false</notifyManagerDelay>
      <allowanceManagerTime>0</allowanceManagerTime>
      <frequenceManagerTime>0</frequenceManagerTime>
      <inhibitTransfer>false</inhibitTransfer>
      <periodId></periodId>
      <stateType>0</stateType>
      <bpmnType>80</bpmnType>
      <signalId>0</signalId>
      <counterSign>false</counterSign>
      <openInstances>0</openInstances>
      <noticeExpirationAuthorityTime>0</noticeExpirationAuthorityTime>
      <noticeExpirationRequisitionerTime>0</noticeExpirationRequisitionerTime>
      <noticeExpirationManagerTime>0</noticeExpirationManagerTime>
      <destinationStates/>
      <digitalSignature>false</digitalSignature>
      <executionType>0</executionType>
    </ProcessState>
    <ProcessState>
      <processStatePK>
        <companyId>1</companyId>
        <processId>wf_cadastro_compra_item_novo</processId>
        <version>1</version>
        <sequence>95</sequence>
      </processStatePK>
      <stateName>Gerente Compras</stateName>
      <stateDescription>Gerente Compras</stateDescription>
      <instruction></instruction>
      <deadlineTime>0</deadlineTime>
      <deadlineFieldName></deadlineFieldName>
      <joint>false</joint>
      <agreementPercentage>0</agreementPercentage>
      <engineAllocationId>Campo Formulário</engineAllocationId>
      <engineAllocationConfiguration>&lt;AssignmentController&gt;&lt;FormField&gt;matcompras4&lt;/FormField&gt;&lt;/AssignmentController&gt;</engineAllocationConfiguration>
      <selectColleague>1</selectColleague>
      <initialState>false</initialState>
      <notifyAuthorityDelay>true</notifyAuthorityDelay>
      <notifyRequisitionerDelay>false</notifyRequisitionerDelay>
      <allowanceAuthorityTime>3600</allowanceAuthorityTime>
      <frequenceAuthorityTime>3600</frequenceAuthorityTime>
      <allowanceRequisitionerTime>0</allowanceRequisitionerTime>
      <frequenceRequisitionerTime>0</frequenceRequisitionerTime>
      <transferAttachments>false</transferAttachments>
      <subProcessId></subProcessId>
      <formFolder>0</formFolder>
      <notifyAuthorityFollowUp>true</notifyAuthorityFollowUp>
      <notifyRequisitionerFollowUp>false</notifyRequisitionerFollowUp>
      <automatic>false</automatic>
      <positionX>591</positionX>
      <positionY>460</positionY>
      <forecastedEffortType>0</forecastedEffortType>
      <forecastedEffort>0</forecastedEffort>
      <notifyManagerFollowUp>false</notifyManagerFollowUp>
      <notifyManagerDelay>false</notifyManagerDelay>
      <allowanceManagerTime>0</allowanceManagerTime>
      <frequenceManagerTime>0</frequenceManagerTime>
      <inhibitTransfer>false</inhibitTransfer>
      <periodId></periodId>
      <stateType>0</stateType>
      <bpmnType>80</bpmnType>
      <signalId>0</signalId>
      <counterSign>false</counterSign>
      <openInstances>0</openInstances>
      <noticeExpirationAuthorityTime>0</noticeExpirationAuthorityTime>
      <noticeExpirationRequisitionerTime>0</noticeExpirationRequisitionerTime>
      <noticeExpirationManagerTime>0</noticeExpirationManagerTime>
      <destinationStates/>
      <digitalSignature>false</digitalSignature>
      <executionType>0</executionType>
    </ProcessState>
    <ProcessState>
      <processStatePK>
        <companyId>1</companyId>
        <processId>wf_cadastro_compra_item_novo</processId>
        <version>1</version>
        <sequence>91</sequence>
      </processStatePK>
      <stateName>Paralelo</stateName>
      <stateDescription>Paralelo</stateDescription>
      <joint>false</joint>
      <initialState>false</initialState>
      <transferAttachments>false</transferAttachments>
      <subProcessId></subProcessId>
      <formFolder>0</formFolder>
      <automatic>false</automatic>
      <positionX>381</positionX>
      <positionY>179</positionY>
      <inhibitTransfer>false</inhibitTransfer>
      <stateType>3</stateType>
      <bpmnType>126</bpmnType>
      <signalId>0</signalId>
      <openInstances>0</openInstances>
      <destinationStates/>
      <digitalSignature>false</digitalSignature>
    </ProcessState>
    <ProcessState>
      <processStatePK>
        <companyId>1</companyId>
        <processId>wf_cadastro_compra_item_novo</processId>
        <version>1</version>
        <sequence>100</sequence>
      </processStatePK>
      <stateName>Join</stateName>
      <stateDescription>Join</stateDescription>
      <joint>false</joint>
      <initialState>false</initialState>
      <transferAttachments>false</transferAttachments>
      <subProcessId></subProcessId>
      <formFolder>0</formFolder>
      <automatic>false</automatic>
      <positionX>381</positionX>
      <positionY>610</positionY>
      <inhibitTransfer>false</inhibitTransfer>
      <stateType>4</stateType>
      <bpmnType>127</bpmnType>
      <signalId>0</signalId>
      <openInstances>0</openInstances>
      <destinationStates/>
      <digitalSignature>false</digitalSignature>
    </ProcessState>
    <ProcessState>
      <processStatePK>
        <companyId>1</companyId>
        <processId>wf_cadastro_compra_item_novo</processId>
        <version>1</version>
        <sequence>106</sequence>
      </processStatePK>
      <stateName>Compras 01?</stateName>
      <stateDescription>Compras 01?</stateDescription>
      <joint>false</joint>
      <initialState>false</initialState>
      <transferAttachments>false</transferAttachments>
      <subProcessId></subProcessId>
      <formFolder>0</formFolder>
      <automatic>true</automatic>
      <positionX>151</positionX>
      <positionY>350</positionY>
      <inhibitTransfer>false</inhibitTransfer>
      <stateType>1</stateType>
      <bpmnType>120</bpmnType>
      <signalId>0</signalId>
      <openInstances>0</openInstances>
      <destinationStates/>
      <digitalSignature>false</digitalSignature>
    </ProcessState>
    <ProcessState>
      <processStatePK>
        <companyId>1</companyId>
        <processId>wf_cadastro_compra_item_novo</processId>
        <version>1</version>
        <sequence>109</sequence>
      </processStatePK>
      <stateName>Compras 02?</stateName>
      <stateDescription>Compras 02?</stateDescription>
      <joint>false</joint>
      <initialState>false</initialState>
      <transferAttachments>false</transferAttachments>
      <subProcessId></subProcessId>
      <formFolder>0</formFolder>
      <automatic>true</automatic>
      <positionX>311</positionX>
      <positionY>350</positionY>
      <inhibitTransfer>false</inhibitTransfer>
      <stateType>1</stateType>
      <bpmnType>120</bpmnType>
      <signalId>0</signalId>
      <openInstances>0</openInstances>
      <destinationStates/>
      <digitalSignature>false</digitalSignature>
    </ProcessState>
    <ProcessState>
      <processStatePK>
        <companyId>1</companyId>
        <processId>wf_cadastro_compra_item_novo</processId>
        <version>1</version>
        <sequence>112</sequence>
      </processStatePK>
      <stateName>Compras 03?</stateName>
      <stateDescription>Compras 03?</stateDescription>
      <joint>false</joint>
      <initialState>false</initialState>
      <transferAttachments>false</transferAttachments>
      <subProcessId></subProcessId>
      <formFolder>0</formFolder>
      <automatic>true</automatic>
      <positionX>461</positionX>
      <positionY>350</positionY>
      <inhibitTransfer>false</inhibitTransfer>
      <stateType>1</stateType>
      <bpmnType>120</bpmnType>
      <signalId>0</signalId>
      <openInstances>0</openInstances>
      <destinationStates/>
      <digitalSignature>false</digitalSignature>
    </ProcessState>
    <ProcessState>
      <processStatePK>
        <companyId>1</companyId>
        <processId>wf_cadastro_compra_item_novo</processId>
        <version>1</version>
        <sequence>115</sequence>
      </processStatePK>
      <stateName>Gerente de compras?</stateName>
      <stateDescription>Gerente de compras?</stateDescription>
      <joint>false</joint>
      <initialState>false</initialState>
      <transferAttachments>false</transferAttachments>
      <subProcessId></subProcessId>
      <formFolder>0</formFolder>
      <automatic>true</automatic>
      <positionX>611</positionX>
      <positionY>350</positionY>
      <inhibitTransfer>false</inhibitTransfer>
      <stateType>1</stateType>
      <bpmnType>120</bpmnType>
      <signalId>0</signalId>
      <openInstances>0</openInstances>
      <destinationStates/>
      <digitalSignature>false</digitalSignature>
    </ProcessState>
    <ProcessState>
      <processStatePK>
        <companyId>1</companyId>
        <processId>wf_cadastro_compra_item_novo</processId>
        <version>1</version>
        <sequence>52</sequence>
      </processStatePK>
      <stateName>Fim - finalizado com sucesso</stateName>
      <stateDescription>Fim - finalizado com sucesso</stateDescription>
      <instruction>Atividade final do processo</instruction>
      <deadlineTime>0</deadlineTime>
      <joint>false</joint>
      <agreementPercentage>0</agreementPercentage>
      <engineAllocationId></engineAllocationId>
      <engineAllocationConfiguration></engineAllocationConfiguration>
      <selectColleague>0</selectColleague>
      <initialState>false</initialState>
      <notifyAuthorityDelay>true</notifyAuthorityDelay>
      <notifyRequisitionerDelay>false</notifyRequisitionerDelay>
      <allowanceAuthorityTime>0</allowanceAuthorityTime>
      <frequenceAuthorityTime>1</frequenceAuthorityTime>
      <allowanceRequisitionerTime>0</allowanceRequisitionerTime>
      <frequenceRequisitionerTime>0</frequenceRequisitionerTime>
      <transferAttachments>false</transferAttachments>
      <subProcessId></subProcessId>
      <formFolder>0</formFolder>
      <notifyAuthorityFollowUp>false</notifyAuthorityFollowUp>
      <notifyRequisitionerFollowUp>false</notifyRequisitionerFollowUp>
      <automatic>false</automatic>
      <positionX>1301</positionX>
      <positionY>205</positionY>
      <forecastedEffortType>0</forecastedEffortType>
      <forecastedEffort>0</forecastedEffort>
      <notifyManagerFollowUp>false</notifyManagerFollowUp>
      <notifyManagerDelay>false</notifyManagerDelay>
      <allowanceManagerTime>0</allowanceManagerTime>
      <frequenceManagerTime>0</frequenceManagerTime>
      <inhibitTransfer>false</inhibitTransfer>
      <periodId></periodId>
      <stateType>6</stateType>
      <bpmnType>60</bpmnType>
      <signalId>0</signalId>
      <counterSign>false</counterSign>
      <openInstances>0</openInstances>
      <destinationStates/>
      <digitalSignature>false</digitalSignature>
    </ProcessState>
  </list>
  <list>
    <ConditionProcessState>
      <conditionProcessStatePK>
        <companyId>1</companyId>
        <processId>wf_cadastro_compra_item_novo</processId>
        <expressionOrder>1</expressionOrder>
        <version>28</version>
        <sequence>106</sequence>
      </conditionProcessStatePK>
      <condition>hAPI.getCardValue(&quot;matcompras1&quot;) == &quot;&quot;</condition>
      <destinationSequenceId>100</destinationSequenceId>
      <conditionType>0</conditionType>
    </ConditionProcessState>
    <ConditionProcessState>
      <conditionProcessStatePK>
        <companyId>1</companyId>
        <processId>wf_cadastro_compra_item_novo</processId>
        <expressionOrder>2</expressionOrder>
        <version>28</version>
        <sequence>106</sequence>
      </conditionProcessStatePK>
      <condition>hAPI.getCardValue(&quot;matcompras1&quot;) != &quot;&quot;</condition>
      <destinationSequenceId>37</destinationSequenceId>
      <conditionType>0</conditionType>
    </ConditionProcessState>
    <ConditionProcessState>
      <conditionProcessStatePK>
        <companyId>1</companyId>
        <processId>wf_cadastro_compra_item_novo</processId>
        <expressionOrder>1</expressionOrder>
        <version>28</version>
        <sequence>109</sequence>
      </conditionProcessStatePK>
      <condition>hAPI.getCardValue(&quot;matcompras2&quot;) == &quot;&quot;</condition>
      <destinationSequenceId>100</destinationSequenceId>
      <conditionType>0</conditionType>
    </ConditionProcessState>
    <ConditionProcessState>
      <conditionProcessStatePK>
        <companyId>1</companyId>
        <processId>wf_cadastro_compra_item_novo</processId>
        <expressionOrder>2</expressionOrder>
        <version>28</version>
        <sequence>109</sequence>
      </conditionProcessStatePK>
      <condition>hAPI.getCardValue(&quot;matcompras2&quot;) != &quot;&quot;</condition>
      <destinationSequenceId>93</destinationSequenceId>
      <conditionType>0</conditionType>
    </ConditionProcessState>
    <ConditionProcessState>
      <conditionProcessStatePK>
        <companyId>1</companyId>
        <processId>wf_cadastro_compra_item_novo</processId>
        <expressionOrder>1</expressionOrder>
        <version>28</version>
        <sequence>112</sequence>
      </conditionProcessStatePK>
      <condition>hAPI.getCardValue(&quot;matcompras3&quot;) == &quot;&quot;</condition>
      <destinationSequenceId>100</destinationSequenceId>
      <conditionType>0</conditionType>
    </ConditionProcessState>
    <ConditionProcessState>
      <conditionProcessStatePK>
        <companyId>1</companyId>
        <processId>wf_cadastro_compra_item_novo</processId>
        <expressionOrder>2</expressionOrder>
        <version>28</version>
        <sequence>112</sequence>
      </conditionProcessStatePK>
      <condition>hAPI.getCardValue(&quot;matcompras3&quot;) != &quot;&quot;</condition>
      <destinationSequenceId>94</destinationSequenceId>
      <conditionType>0</conditionType>
    </ConditionProcessState>
    <ConditionProcessState>
      <conditionProcessStatePK>
        <companyId>1</companyId>
        <processId>wf_cadastro_compra_item_novo</processId>
        <expressionOrder>1</expressionOrder>
        <version>28</version>
        <sequence>115</sequence>
      </conditionProcessStatePK>
      <condition>hAPI.getCardValue(&quot;matcompras4&quot;) == &quot;&quot;</condition>
      <destinationSequenceId>100</destinationSequenceId>
      <conditionType>0</conditionType>
    </ConditionProcessState>
    <ConditionProcessState>
      <conditionProcessStatePK>
        <companyId>1</companyId>
        <processId>wf_cadastro_compra_item_novo</processId>
        <expressionOrder>2</expressionOrder>
        <version>28</version>
        <sequence>115</sequence>
      </conditionProcessStatePK>
      <condition>hAPI.getCardValue(&quot;matcompras4&quot;) != &quot;&quot;</condition>
      <destinationSequenceId>95</destinationSequenceId>
      <conditionType>0</conditionType>
    </ConditionProcessState>
  </list>
  <list>
    <ProcessLink>
      <processLinkPK>
        <companyId>1</companyId>
        <processId>wf_cadastro_compra_item_novo</processId>
        <version>1</version>
        <linkSequence>71</linkSequence>
      </processLinkPK>
      <actionLabel></actionLabel>
      <returnPermited>false</returnPermited>
      <initialStateSequence>3</initialStateSequence>
      <finalStateSequence>20</finalStateSequence>
      <returnLabel></returnLabel>
      <name></name>
      <automaticLink>false</automaticLink>
      <defaultLink>false</defaultLink>
      <type>0</type>
    </ProcessLink>
    <ProcessLink>
      <processLinkPK>
        <companyId>1</companyId>
        <processId>wf_cadastro_compra_item_novo</processId>
        <version>1</version>
        <linkSequence>79</linkSequence>
      </processLinkPK>
      <actionLabel></actionLabel>
      <returnPermited>false</returnPermited>
      <initialStateSequence>20</initialStateSequence>
      <finalStateSequence>73</finalStateSequence>
      <returnLabel></returnLabel>
      <name></name>
      <automaticLink>false</automaticLink>
      <defaultLink>false</defaultLink>
      <type>0</type>
    </ProcessLink>
    <ProcessLink>
      <processLinkPK>
        <companyId>1</companyId>
        <processId>wf_cadastro_compra_item_novo</processId>
        <version>1</version>
        <linkSequence>83</linkSequence>
      </processLinkPK>
      <actionLabel></actionLabel>
      <returnPermited>false</returnPermited>
      <initialStateSequence>81</initialStateSequence>
      <finalStateSequence>10</finalStateSequence>
      <returnLabel></returnLabel>
      <name></name>
      <automaticLink>false</automaticLink>
      <defaultLink>false</defaultLink>
      <type>0</type>
    </ProcessLink>
    <ProcessLink>
      <processLinkPK>
        <companyId>1</companyId>
        <processId>wf_cadastro_compra_item_novo</processId>
        <version>1</version>
        <linkSequence>84</linkSequence>
      </processLinkPK>
      <actionLabel></actionLabel>
      <returnPermited>false</returnPermited>
      <initialStateSequence>10</initialStateSequence>
      <finalStateSequence>75</finalStateSequence>
      <returnLabel></returnLabel>
      <name></name>
      <automaticLink>false</automaticLink>
      <defaultLink>false</defaultLink>
      <type>0</type>
    </ProcessLink>
    <ProcessLink>
      <processLinkPK>
        <companyId>1</companyId>
        <processId>wf_cadastro_compra_item_novo</processId>
        <version>1</version>
        <linkSequence>86</linkSequence>
      </processLinkPK>
      <actionLabel></actionLabel>
      <returnPermited>false</returnPermited>
      <initialStateSequence>75</initialStateSequence>
      <finalStateSequence>85</finalStateSequence>
      <returnLabel></returnLabel>
      <name></name>
      <automaticLink>false</automaticLink>
      <defaultLink>false</defaultLink>
      <type>0</type>
    </ProcessLink>
    <ProcessLink>
      <processLinkPK>
        <companyId>1</companyId>
        <processId>wf_cadastro_compra_item_novo</processId>
        <version>1</version>
        <linkSequence>88</linkSequence>
      </processLinkPK>
      <actionLabel></actionLabel>
      <returnPermited>false</returnPermited>
      <initialStateSequence>85</initialStateSequence>
      <finalStateSequence>87</finalStateSequence>
      <returnLabel></returnLabel>
      <name></name>
      <automaticLink>false</automaticLink>
      <defaultLink>false</defaultLink>
      <type>0</type>
    </ProcessLink>
    <ProcessLink>
      <processLinkPK>
        <companyId>1</companyId>
        <processId>wf_cadastro_compra_item_novo</processId>
        <version>1</version>
        <linkSequence>89</linkSequence>
      </processLinkPK>
      <actionLabel></actionLabel>
      <returnPermited>false</returnPermited>
      <initialStateSequence>87</initialStateSequence>
      <finalStateSequence>52</finalStateSequence>
      <returnLabel></returnLabel>
      <name></name>
      <automaticLink>false</automaticLink>
      <defaultLink>false</defaultLink>
      <type>0</type>
    </ProcessLink>
    <ProcessLink>
      <processLinkPK>
        <companyId>1</companyId>
        <processId>wf_cadastro_compra_item_novo</processId>
        <version>1</version>
        <linkSequence>92</linkSequence>
      </processLinkPK>
      <actionLabel></actionLabel>
      <returnPermited>false</returnPermited>
      <initialStateSequence>73</initialStateSequence>
      <finalStateSequence>91</finalStateSequence>
      <returnLabel></returnLabel>
      <name></name>
      <automaticLink>false</automaticLink>
      <defaultLink>false</defaultLink>
      <type>0</type>
    </ProcessLink>
    <ProcessLink>
      <processLinkPK>
        <companyId>1</companyId>
        <processId>wf_cadastro_compra_item_novo</processId>
        <version>1</version>
        <linkSequence>101</linkSequence>
      </processLinkPK>
      <actionLabel></actionLabel>
      <returnPermited>false</returnPermited>
      <initialStateSequence>37</initialStateSequence>
      <finalStateSequence>100</finalStateSequence>
      <returnLabel></returnLabel>
      <name></name>
      <automaticLink>false</automaticLink>
      <defaultLink>false</defaultLink>
      <type>0</type>
    </ProcessLink>
    <ProcessLink>
      <processLinkPK>
        <companyId>1</companyId>
        <processId>wf_cadastro_compra_item_novo</processId>
        <version>1</version>
        <linkSequence>102</linkSequence>
      </processLinkPK>
      <actionLabel></actionLabel>
      <returnPermited>false</returnPermited>
      <initialStateSequence>93</initialStateSequence>
      <finalStateSequence>100</finalStateSequence>
      <returnLabel></returnLabel>
      <name></name>
      <automaticLink>false</automaticLink>
      <defaultLink>false</defaultLink>
      <type>0</type>
    </ProcessLink>
    <ProcessLink>
      <processLinkPK>
        <companyId>1</companyId>
        <processId>wf_cadastro_compra_item_novo</processId>
        <version>1</version>
        <linkSequence>103</linkSequence>
      </processLinkPK>
      <actionLabel></actionLabel>
      <returnPermited>false</returnPermited>
      <initialStateSequence>94</initialStateSequence>
      <finalStateSequence>100</finalStateSequence>
      <returnLabel></returnLabel>
      <name></name>
      <automaticLink>false</automaticLink>
      <defaultLink>false</defaultLink>
      <type>0</type>
    </ProcessLink>
    <ProcessLink>
      <processLinkPK>
        <companyId>1</companyId>
        <processId>wf_cadastro_compra_item_novo</processId>
        <version>1</version>
        <linkSequence>104</linkSequence>
      </processLinkPK>
      <actionLabel></actionLabel>
      <returnPermited>false</returnPermited>
      <initialStateSequence>95</initialStateSequence>
      <finalStateSequence>100</finalStateSequence>
      <returnLabel></returnLabel>
      <name></name>
      <automaticLink>false</automaticLink>
      <defaultLink>false</defaultLink>
      <type>0</type>
    </ProcessLink>
    <ProcessLink>
      <processLinkPK>
        <companyId>1</companyId>
        <processId>wf_cadastro_compra_item_novo</processId>
        <version>1</version>
        <linkSequence>107</linkSequence>
      </processLinkPK>
      <actionLabel></actionLabel>
      <returnPermited>false</returnPermited>
      <initialStateSequence>106</initialStateSequence>
      <finalStateSequence>37</finalStateSequence>
      <returnLabel></returnLabel>
      <name></name>
      <automaticLink>false</automaticLink>
      <defaultLink>false</defaultLink>
      <type>0</type>
    </ProcessLink>
    <ProcessLink>
      <processLinkPK>
        <companyId>1</companyId>
        <processId>wf_cadastro_compra_item_novo</processId>
        <version>1</version>
        <linkSequence>108</linkSequence>
      </processLinkPK>
      <actionLabel></actionLabel>
      <returnPermited>false</returnPermited>
      <initialStateSequence>106</initialStateSequence>
      <finalStateSequence>100</finalStateSequence>
      <returnLabel></returnLabel>
      <name></name>
      <automaticLink>false</automaticLink>
      <defaultLink>false</defaultLink>
      <type>0</type>
    </ProcessLink>
    <ProcessLink>
      <processLinkPK>
        <companyId>1</companyId>
        <processId>wf_cadastro_compra_item_novo</processId>
        <version>1</version>
        <linkSequence>110</linkSequence>
      </processLinkPK>
      <actionLabel></actionLabel>
      <returnPermited>false</returnPermited>
      <initialStateSequence>109</initialStateSequence>
      <finalStateSequence>93</finalStateSequence>
      <returnLabel></returnLabel>
      <name></name>
      <automaticLink>false</automaticLink>
      <defaultLink>false</defaultLink>
      <type>0</type>
    </ProcessLink>
    <ProcessLink>
      <processLinkPK>
        <companyId>1</companyId>
        <processId>wf_cadastro_compra_item_novo</processId>
        <version>1</version>
        <linkSequence>111</linkSequence>
      </processLinkPK>
      <actionLabel></actionLabel>
      <returnPermited>false</returnPermited>
      <initialStateSequence>109</initialStateSequence>
      <finalStateSequence>100</finalStateSequence>
      <returnLabel></returnLabel>
      <name></name>
      <automaticLink>false</automaticLink>
      <defaultLink>false</defaultLink>
      <type>0</type>
    </ProcessLink>
    <ProcessLink>
      <processLinkPK>
        <companyId>1</companyId>
        <processId>wf_cadastro_compra_item_novo</processId>
        <version>1</version>
        <linkSequence>113</linkSequence>
      </processLinkPK>
      <actionLabel></actionLabel>
      <returnPermited>false</returnPermited>
      <initialStateSequence>112</initialStateSequence>
      <finalStateSequence>94</finalStateSequence>
      <returnLabel></returnLabel>
      <name></name>
      <automaticLink>false</automaticLink>
      <defaultLink>false</defaultLink>
      <type>0</type>
    </ProcessLink>
    <ProcessLink>
      <processLinkPK>
        <companyId>1</companyId>
        <processId>wf_cadastro_compra_item_novo</processId>
        <version>1</version>
        <linkSequence>114</linkSequence>
      </processLinkPK>
      <actionLabel></actionLabel>
      <returnPermited>false</returnPermited>
      <initialStateSequence>112</initialStateSequence>
      <finalStateSequence>100</finalStateSequence>
      <returnLabel></returnLabel>
      <name></name>
      <automaticLink>false</automaticLink>
      <defaultLink>false</defaultLink>
      <type>0</type>
    </ProcessLink>
    <ProcessLink>
      <processLinkPK>
        <companyId>1</companyId>
        <processId>wf_cadastro_compra_item_novo</processId>
        <version>1</version>
        <linkSequence>116</linkSequence>
      </processLinkPK>
      <actionLabel></actionLabel>
      <returnPermited>false</returnPermited>
      <initialStateSequence>115</initialStateSequence>
      <finalStateSequence>95</finalStateSequence>
      <returnLabel></returnLabel>
      <name></name>
      <automaticLink>false</automaticLink>
      <defaultLink>false</defaultLink>
      <type>0</type>
    </ProcessLink>
    <ProcessLink>
      <processLinkPK>
        <companyId>1</companyId>
        <processId>wf_cadastro_compra_item_novo</processId>
        <version>1</version>
        <linkSequence>117</linkSequence>
      </processLinkPK>
      <actionLabel></actionLabel>
      <returnPermited>false</returnPermited>
      <initialStateSequence>115</initialStateSequence>
      <finalStateSequence>100</finalStateSequence>
      <returnLabel></returnLabel>
      <name></name>
      <automaticLink>false</automaticLink>
      <defaultLink>false</defaultLink>
      <type>0</type>
    </ProcessLink>
    <ProcessLink>
      <processLinkPK>
        <companyId>1</companyId>
        <processId>wf_cadastro_compra_item_novo</processId>
        <version>1</version>
        <linkSequence>118</linkSequence>
      </processLinkPK>
      <actionLabel></actionLabel>
      <returnPermited>false</returnPermited>
      <initialStateSequence>91</initialStateSequence>
      <finalStateSequence>106</finalStateSequence>
      <returnLabel></returnLabel>
      <name></name>
      <automaticLink>false</automaticLink>
      <defaultLink>false</defaultLink>
      <type>0</type>
    </ProcessLink>
    <ProcessLink>
      <processLinkPK>
        <companyId>1</companyId>
        <processId>wf_cadastro_compra_item_novo</processId>
        <version>1</version>
        <linkSequence>119</linkSequence>
      </processLinkPK>
      <actionLabel></actionLabel>
      <returnPermited>false</returnPermited>
      <initialStateSequence>91</initialStateSequence>
      <finalStateSequence>109</finalStateSequence>
      <returnLabel></returnLabel>
      <name></name>
      <automaticLink>false</automaticLink>
      <defaultLink>false</defaultLink>
      <type>0</type>
    </ProcessLink>
    <ProcessLink>
      <processLinkPK>
        <companyId>1</companyId>
        <processId>wf_cadastro_compra_item_novo</processId>
        <version>1</version>
        <linkSequence>120</linkSequence>
      </processLinkPK>
      <actionLabel></actionLabel>
      <returnPermited>false</returnPermited>
      <initialStateSequence>91</initialStateSequence>
      <finalStateSequence>112</finalStateSequence>
      <returnLabel></returnLabel>
      <name></name>
      <automaticLink>false</automaticLink>
      <defaultLink>false</defaultLink>
      <type>0</type>
    </ProcessLink>
    <ProcessLink>
      <processLinkPK>
        <companyId>1</companyId>
        <processId>wf_cadastro_compra_item_novo</processId>
        <version>1</version>
        <linkSequence>121</linkSequence>
      </processLinkPK>
      <actionLabel></actionLabel>
      <returnPermited>false</returnPermited>
      <initialStateSequence>91</initialStateSequence>
      <finalStateSequence>115</finalStateSequence>
      <returnLabel></returnLabel>
      <name></name>
      <automaticLink>false</automaticLink>
      <defaultLink>false</defaultLink>
      <type>0</type>
    </ProcessLink>
    <ProcessLink>
      <processLinkPK>
        <companyId>1</companyId>
        <processId>wf_cadastro_compra_item_novo</processId>
        <version>1</version>
        <linkSequence>122</linkSequence>
      </processLinkPK>
      <actionLabel></actionLabel>
      <returnPermited>false</returnPermited>
      <initialStateSequence>100</initialStateSequence>
      <finalStateSequence>81</finalStateSequence>
      <returnLabel></returnLabel>
      <name></name>
      <automaticLink>false</automaticLink>
      <defaultLink>false</defaultLink>
      <type>0</type>
    </ProcessLink>
  </list>
  <list/>
  <list>
    <WorkflowProcessEvent>
      <workflowProcessEventPK>
        <companyId>1</companyId>
        <eventId>afterTaskComplete</eventId>
        <processId>wf_cadastro_compra_item_novo</processId>
        <version>1</version>
      </workflowProcessEventPK>
      <eventDescription>function afterTaskComplete(colleagueId,nextSequenceId,userList){  &#xd;
             &#xd;
        var num_processo = getValue (&quot;WKNumProces&quot;);     &#xd;
        var usuario = getValue (&quot;WKUser&quot;);   &#xd;
    &#xd;
        var observacao = hAPI.getCardValue(&quot;observacao&quot;);&#xd;
        var compras = hAPI.getCardValue(&quot;obscompras&quot;);&#xd;
        var recebimento = hAPI.getCardValue(&quot;obsreceb&quot;);&#xd;
        var rastreio = hAPI.getCardValue(&quot;obsrastreio&quot;);&#xd;
        var liberacao = hAPI.getCardValue(&quot;obsliberacao&quot;);&#xd;
        var fim = hAPI.getCardValue(&quot;obsfim&quot;);&#xd;
&#xd;
        if(nextSequenceId==20){     &#xd;
                hAPI.setTaskComments(usuario, num_processo, 0, observacao);                    &#xd;
        } &#xd;
    &#xd;
        if(nextSequenceId==10){    &#xd;
                hAPI.setTaskComments(usuario, num_processo, 0, compras);                   &#xd;
        } &#xd;
    &#xd;
        if(nextSequenceId==37){     &#xd;
                hAPI.setTaskComments(usuario, num_processo, 0, recebimento);                     &#xd;
        } &#xd;
    &#xd;
        if(nextSequenceId==73){         &#xd;
                hAPI.setTaskComments(usuario, num_processo, 0, rastreio);                    &#xd;
        } &#xd;
    &#xd;
        if(nextSequenceId==75){   &#xd;
                hAPI.setTaskComments(usuario, num_processo, 0, liberacao);                              &#xd;
        }      &#xd;
&#xd;
        if(nextSequenceId==52){   &#xd;
                hAPI.setTaskComments(usuario, num_processo, 0, fim);                    &#xd;
        }   &#xd;
   &#xd;
}</eventDescription>
    </WorkflowProcessEvent>
    <WorkflowProcessEvent>
      <workflowProcessEventPK>
        <companyId>1</companyId>
        <eventId>beforeCancelProcess</eventId>
        <processId>wf_cadastro_compra_item_novo</processId>
        <version>1</version>
      </workflowProcessEventPK>
      <eventDescription>function beforeCancelProcess(colleagueId, processId) {&#xd;
    // Verifique se o usuário atual (colleagueId) é igual a 209&#xd;
    if (colleagueId == 209) {&#xd;
        // Permite que o processo seja cancelado&#xd;
        return true;&#xd;
    } else {&#xd;
        // Impede que o processo seja cancelado&#xd;
        throw &quot;Apenas o usuário Maicon Conceição pode cancelar este processo.&quot;;&#xd;
    }&#xd;
}&#xd;
</eventDescription>
    </WorkflowProcessEvent>
  </list>
  <list/>
  <list>
    <SwimLane>
      <color>9fc1c6</color>
      <height>150</height>
      <width>1372</width>
      <positionX>0</positionX>
      <positionY>0</positionY>
      <stateName>Vendas</stateName>
      <type>2</type>
      <parentSequence>0</parentSequence>
      <swimLanePK>
        <companyId>1</companyId>
        <processId>wf_cadastro_compra_item_novo</processId>
        <version>1</version>
        <sequence>1</sequence>
      </swimLanePK>
    </SwimLane>
    <SwimLane>
      <color>d0daae</color>
      <height>145</height>
      <width>1372</width>
      <positionX>0</positionX>
      <positionY>149</positionY>
      <stateName>Compras</stateName>
      <type>2</type>
      <parentSequence>0</parentSequence>
      <swimLanePK>
        <companyId>1</companyId>
        <processId>wf_cadastro_compra_item_novo</processId>
        <version>1</version>
        <sequence>2</sequence>
      </swimLanePK>
    </SwimLane>
    <SwimLane>
      <color>82b0b7</color>
      <height>150</height>
      <width>1372</width>
      <positionX>1</positionX>
      <positionY>568</positionY>
      <stateName>Recebimento</stateName>
      <type>2</type>
      <parentSequence>0</parentSequence>
      <swimLanePK>
        <companyId>1</companyId>
        <processId>wf_cadastro_compra_item_novo</processId>
        <version>1</version>
        <sequence>3</sequence>
      </swimLanePK>
    </SwimLane>
    <SwimLane>
      <color>adc9ac</color>
      <height>278</height>
      <width>1371</width>
      <positionX>1</positionX>
      <positionY>293</positionY>
      <stateName>SwimLane</stateName>
      <type>2</type>
      <parentSequence>0</parentSequence>
      <swimLanePK>
        <companyId>1</companyId>
        <processId>wf_cadastro_compra_item_novo</processId>
        <version>1</version>
        <sequence>4</sequence>
      </swimLanePK>
    </SwimLane>
  </list>
  <list/>
  <list/>
  <list>
    <ProcessLinkBend>
      <processLinkBendPK>
        <companyId>1</companyId>
        <processId>wf_cadastro_compra_item_novo</processId>
        <version>28</version>
        <linkSequence>71</linkSequence>
        <bendSequence>1</bendSequence>
      </processLinkBendPK>
      <positionX>88</positionX>
      <positionY>224</positionY>
    </ProcessLinkBend>
    <ProcessLinkBend>
      <processLinkBendPK>
        <companyId>1</companyId>
        <processId>wf_cadastro_compra_item_novo</processId>
        <version>28</version>
        <linkSequence>79</linkSequence>
        <bendSequence>1</bendSequence>
      </processLinkBendPK>
      <positionX>174</positionX>
      <positionY>77</positionY>
    </ProcessLinkBend>
    <ProcessLinkBend>
      <processLinkBendPK>
        <companyId>1</companyId>
        <processId>wf_cadastro_compra_item_novo</processId>
        <version>28</version>
        <linkSequence>83</linkSequence>
        <bendSequence>1</bendSequence>
      </processLinkBendPK>
      <positionX>844</positionX>
      <positionY>369</positionY>
    </ProcessLinkBend>
    <ProcessLinkBend>
      <processLinkBendPK>
        <companyId>1</companyId>
        <processId>wf_cadastro_compra_item_novo</processId>
        <version>28</version>
        <linkSequence>84</linkSequence>
        <bendSequence>1</bendSequence>
      </processLinkBendPK>
      <positionX>1034</positionX>
      <positionY>370</positionY>
    </ProcessLinkBend>
    <ProcessLinkBend>
      <processLinkBendPK>
        <companyId>1</companyId>
        <processId>wf_cadastro_compra_item_novo</processId>
        <version>28</version>
        <linkSequence>84</linkSequence>
        <bendSequence>2</bendSequence>
      </processLinkBendPK>
      <positionX>1034</positionX>
      <positionY>328</positionY>
    </ProcessLinkBend>
    <ProcessLinkBend>
      <processLinkBendPK>
        <companyId>1</companyId>
        <processId>wf_cadastro_compra_item_novo</processId>
        <version>28</version>
        <linkSequence>86</linkSequence>
        <bendSequence>1</bendSequence>
      </processLinkBendPK>
      <positionX>1034</positionX>
      <positionY>84</positionY>
    </ProcessLinkBend>
    <ProcessLinkBend>
      <processLinkBendPK>
        <companyId>1</companyId>
        <processId>wf_cadastro_compra_item_novo</processId>
        <version>28</version>
        <linkSequence>88</linkSequence>
        <bendSequence>1</bendSequence>
      </processLinkBendPK>
      <positionX>1204</positionX>
      <positionY>85</positionY>
    </ProcessLinkBend>
    <ProcessLinkBend>
      <processLinkBendPK>
        <companyId>1</companyId>
        <processId>wf_cadastro_compra_item_novo</processId>
        <version>28</version>
        <linkSequence>92</linkSequence>
        <bendSequence>1</bendSequence>
      </processLinkBendPK>
      <positionX>412</positionX>
      <positionY>77</positionY>
    </ProcessLinkBend>
    <ProcessLinkBend>
      <processLinkBendPK>
        <companyId>1</companyId>
        <processId>wf_cadastro_compra_item_novo</processId>
        <version>28</version>
        <linkSequence>101</linkSequence>
        <bendSequence>1</bendSequence>
      </processLinkBendPK>
      <positionX>183</positionX>
      <positionY>654</positionY>
    </ProcessLinkBend>
    <ProcessLinkBend>
      <processLinkBendPK>
        <companyId>1</companyId>
        <processId>wf_cadastro_compra_item_novo</processId>
        <version>28</version>
        <linkSequence>102</linkSequence>
        <bendSequence>1</bendSequence>
      </processLinkBendPK>
      <positionX>343</positionX>
      <positionY>624</positionY>
    </ProcessLinkBend>
    <ProcessLinkBend>
      <processLinkBendPK>
        <companyId>1</companyId>
        <processId>wf_cadastro_compra_item_novo</processId>
        <version>28</version>
        <linkSequence>103</linkSequence>
        <bendSequence>1</bendSequence>
      </processLinkBendPK>
      <positionX>493</positionX>
      <positionY>596</positionY>
    </ProcessLinkBend>
    <ProcessLinkBend>
      <processLinkBendPK>
        <companyId>1</companyId>
        <processId>wf_cadastro_compra_item_novo</processId>
        <version>28</version>
        <linkSequence>104</linkSequence>
        <bendSequence>1</bendSequence>
      </processLinkBendPK>
      <positionX>643</positionX>
      <positionY>621</positionY>
    </ProcessLinkBend>
    <ProcessLinkBend>
      <processLinkBendPK>
        <companyId>1</companyId>
        <processId>wf_cadastro_compra_item_novo</processId>
        <version>28</version>
        <linkSequence>108</linkSequence>
        <bendSequence>1</bendSequence>
      </processLinkBendPK>
      <positionX>96</positionX>
      <positionY>400</positionY>
    </ProcessLinkBend>
    <ProcessLinkBend>
      <processLinkBendPK>
        <companyId>1</companyId>
        <processId>wf_cadastro_compra_item_novo</processId>
        <version>28</version>
        <linkSequence>108</linkSequence>
        <bendSequence>2</bendSequence>
      </processLinkBendPK>
      <positionX>96</positionX>
      <positionY>653</positionY>
    </ProcessLinkBend>
    <ProcessLinkBend>
      <processLinkBendPK>
        <companyId>1</companyId>
        <processId>wf_cadastro_compra_item_novo</processId>
        <version>28</version>
        <linkSequence>111</linkSequence>
        <bendSequence>1</bendSequence>
      </processLinkBendPK>
      <positionX>261</positionX>
      <positionY>400</positionY>
    </ProcessLinkBend>
    <ProcessLinkBend>
      <processLinkBendPK>
        <companyId>1</companyId>
        <processId>wf_cadastro_compra_item_novo</processId>
        <version>28</version>
        <linkSequence>111</linkSequence>
        <bendSequence>2</bendSequence>
      </processLinkBendPK>
      <positionX>261</positionX>
      <positionY>589</positionY>
    </ProcessLinkBend>
    <ProcessLinkBend>
      <processLinkBendPK>
        <companyId>1</companyId>
        <processId>wf_cadastro_compra_item_novo</processId>
        <version>28</version>
        <linkSequence>114</linkSequence>
        <bendSequence>1</bendSequence>
      </processLinkBendPK>
      <positionX>569</positionX>
      <positionY>401</positionY>
    </ProcessLinkBend>
    <ProcessLinkBend>
      <processLinkBendPK>
        <companyId>1</companyId>
        <processId>wf_cadastro_compra_item_novo</processId>
        <version>28</version>
        <linkSequence>114</linkSequence>
        <bendSequence>2</bendSequence>
      </processLinkBendPK>
      <positionX>569</positionX>
      <positionY>542</positionY>
    </ProcessLinkBend>
    <ProcessLinkBend>
      <processLinkBendPK>
        <companyId>1</companyId>
        <processId>wf_cadastro_compra_item_novo</processId>
        <version>28</version>
        <linkSequence>117</linkSequence>
        <bendSequence>1</bendSequence>
      </processLinkBendPK>
      <positionX>724</positionX>
      <positionY>407</positionY>
    </ProcessLinkBend>
    <ProcessLinkBend>
      <processLinkBendPK>
        <companyId>1</companyId>
        <processId>wf_cadastro_compra_item_novo</processId>
        <version>28</version>
        <linkSequence>117</linkSequence>
        <bendSequence>2</bendSequence>
      </processLinkBendPK>
      <positionX>724</positionX>
      <positionY>608</positionY>
    </ProcessLinkBend>
    <ProcessLinkBend>
      <processLinkBendPK>
        <companyId>1</companyId>
        <processId>wf_cadastro_compra_item_novo</processId>
        <version>28</version>
        <linkSequence>122</linkSequence>
        <bendSequence>1</bendSequence>
      </processLinkBendPK>
      <positionX>742</positionX>
      <positionY>653</positionY>
    </ProcessLinkBend>
    <ProcessLinkBend>
      <processLinkBendPK>
        <companyId>1</companyId>
        <processId>wf_cadastro_compra_item_novo</processId>
        <version>28</version>
        <linkSequence>122</linkSequence>
        <bendSequence>2</bendSequence>
      </processLinkBendPK>
      <positionX>742</positionX>
      <positionY>222</positionY>
    </ProcessLinkBend>
  </list>
  <list/>
  <list/>
  <list>
    <ProcessFormField>
      <processFormFieldPK>
        <companyId>1</companyId>
        <processId>wf_cadastro_compra_item_novo</processId>
        <fieldId>cliente</fieldId>
      </processFormFieldPK>
      <fieldDescription>cliente</fieldDescription>
      <slotId>1</slotId>
    </ProcessFormField>
    <ProcessFormField>
      <processFormFieldPK>
        <companyId>1</companyId>
        <processId>wf_cadastro_compra_item_novo</processId>
        <fieldId>validacao</fieldId>
      </processFormFieldPK>
      <fieldDescription>validacao</fieldDescription>
      <slotId>2</slotId>
    </ProcessFormField>
  </list>
  <list/>
  <list/>
  <list/>
  <list/>
  <list/>
</list>